setup.py
distribs_probability/Binomialdistribution.py
distribs_probability/Gaussiandistribution.py
distribs_probability/Generaldistribution.py
distribs_probability/__init__.py
distribs_probability.egg-info/PKG-INFO
distribs_probability.egg-info/SOURCES.txt
distribs_probability.egg-info/dependency_links.txt
distribs_probability.egg-info/not-zip-safe
distribs_probability.egg-info/top_level.txt