Metadata-Version: 1.0
Name: distribs-probability
Version: 0.1.1
Summary: All probability distributions
Home-page: UNKNOWN
Author: UNKNOWN
Author-email: UNKNOWN
License: UNKNOWN
Platform: UNKNOWN
